bsb_test/__init__.py
bsb_test/debug.py
bsb_test/engines.py
bsb_test/exceptions.py
bsb_test/parallel.py
bsb_test/configs/__init__.py
bsb_test/configs/brunel.py
bsb_test/configs/brunel_wbsb.py
bsb_test/configs/chunked.py
bsb_test/configs/complete.py
bsb_test/configs/double_neuron.py
bsb_test/configs/full_compile.py
bsb_test/configs/gif_pop_psc_exp.py
bsb_test/configs/indegree.py
bsb_test/configs/minimal.py
bsb_test/configs/multi.py
bsb_test/configs/nest_minimal.py
bsb_test/configs/neuron_miniature_sim.py
bsb_test/configs/neuron_minimal.py
bsb_test/configs/outdegree.py
bsb_test/configs/single.py
bsb_test/data/.gitignore
bsb_test/data/morphologies/2branch.swc
bsb_test/data/morphologies/2comp.swc
bsb_test/data/morphologies/2root.swc
bsb_test/data/morphologies/3branch.swc
bsb_test/data/morphologies/AA0048.swc
bsb_test/data/morphologies/BasketCell.swc
bsb_test/data/morphologies/GolgiCell.asc
bsb_test/data/morphologies/GolgiCell.swc
bsb_test/data/morphologies/GranuleCell.swc
bsb_test/data/morphologies/PurkinjeCell.swc
bsb_test/data/morphologies/StellateCell.swc
bsb_test/data/morphologies/soma_boundary.swc
bsb_test/data/morphologies/test_morphometry.swc
bsb_test/data/orientations/toy_annotations.nrrd
bsb_test/data/orientations/toy_orientations.nrrd
bsb_test-7.2.1.dist-info/licenses/LICENSE
bsb_test-7.2.1.dist-info/WHEEL
bsb_test-7.2.1.dist-info/METADATA
bsb_test-7.2.1.dist-info/RECORD
